aicmd/__init__.py
aicmd/__main__.py
aicmd/config.py
aicmd/main.py
aicmd/openai_api.py
aicmd/prompts.py
aicmd/utils.py
tests/__init__.py
tests/test_aicmd.py
noumandaavigi-0.7.dist-info/LICENSE
noumandaavigi-0.7.dist-info/METADATA
noumandaavigi-0.7.dist-info/WHEEL
noumandaavigi-0.7.dist-info/entry_points.txt
noumandaavigi-0.7.dist-info/top_level.txt
noumandaavigi-0.7.dist-info/RECORD
